sfc/__init__.py
sfc/sfc.py
simple_file_configuration-1.0.5.dist-info/LICENSE
simple_file_configuration-1.0.5.dist-info/METADATA
simple_file_configuration-1.0.5.dist-info/WHEEL
simple_file_configuration-1.0.5.dist-info/top_level.txt
simple_file_configuration-1.0.5.dist-info/RECORD
