Metadata-Version: 2.1
Name: simple-file-configuration
Version: 1.0.5
Summary: Simple File Configurations (not only) for Discord Bots
Home-page: https://github.com/xImAnton/simple-file-configuration.py
Author: xImAnton_
Author-email: admin@ximanton.de
Project-URL: Bug Tracker, https://github.com/xImAnton/simple-file-configuration.py/issues
Classifier: Programming Language :: Python :: 3
Classifier: License :: OSI Approved :: MIT License
Classifier: Operating System :: OS Independent
Requires-Python: >=3.8
License-File: LICENSE
